google/cloud/speech/__init__.py
google/cloud/speech/gapic_version.py
google/cloud/speech/py.typed
google/cloud/speech_v1/__init__.py
google/cloud/speech_v1/gapic_metadata.json
google/cloud/speech_v1/gapic_version.py
google/cloud/speech_v1/helpers.py
google/cloud/speech_v1/py.typed
google/cloud/speech_v1/services/__init__.py
google/cloud/speech_v1/services/adaptation/__init__.py
google/cloud/speech_v1/services/adaptation/async_client.py
google/cloud/speech_v1/services/adaptation/client.py
google/cloud/speech_v1/services/adaptation/pagers.py
google/cloud/speech_v1/services/adaptation/transports/__init__.py
google/cloud/speech_v1/services/adaptation/transports/base.py
google/cloud/speech_v1/services/adaptation/transports/grpc.py
google/cloud/speech_v1/services/adaptation/transports/grpc_asyncio.py
google/cloud/speech_v1/services/adaptation/transports/rest.py
google/cloud/speech_v1/services/adaptation/transports/rest_base.py
google/cloud/speech_v1/services/speech/__init__.py
google/cloud/speech_v1/services/speech/async_client.py
google/cloud/speech_v1/services/speech/client.py
google/cloud/speech_v1/services/speech/transports/__init__.py
google/cloud/speech_v1/services/speech/transports/base.py
google/cloud/speech_v1/services/speech/transports/grpc.py
google/cloud/speech_v1/services/speech/transports/grpc_asyncio.py
google/cloud/speech_v1/services/speech/transports/rest.py
google/cloud/speech_v1/services/speech/transports/rest_base.py
google/cloud/speech_v1/types/__init__.py
google/cloud/speech_v1/types/cloud_speech.py
google/cloud/speech_v1/types/cloud_speech_adaptation.py
google/cloud/speech_v1/types/resource.py
google/cloud/speech_v1p1beta1/__init__.py
google/cloud/speech_v1p1beta1/gapic_metadata.json
google/cloud/speech_v1p1beta1/gapic_version.py
google/cloud/speech_v1p1beta1/py.typed
google/cloud/speech_v1p1beta1/services/__init__.py
google/cloud/speech_v1p1beta1/services/adaptation/__init__.py
google/cloud/speech_v1p1beta1/services/adaptation/async_client.py
google_cloud_speech-2.32.0.dist-info/LICENSE
google_cloud_speech-2.32.0.dist-info/METADATA
google_cloud_speech-2.32.0.dist-info/WHEEL
google_cloud_speech-2.32.0.dist-info/top_level.txt
google_cloud_speech-2.32.0.dist-info/RECORD
